netbox_juniper/__init__.py
netbox_juniper/navigation.py
netbox_juniper/urls.py
netbox_juniper/api/__init__.py
netbox_juniper/api/serializers.py
netbox_juniper/api/urls.py
netbox_juniper/api/views.py
netbox_juniper/filtersets/__init__.py
netbox_juniper/filtersets/applications.py
netbox_juniper/filtersets/security.py
netbox_juniper/forms/__init__.py
netbox_juniper/forms/bulk_edit.py
netbox_juniper/forms/bulk_import.py
netbox_juniper/forms/filtersets.py
netbox_juniper/forms/model.py
netbox_juniper/graphql/__init__.py
netbox_juniper/graphql/filters.py
netbox_juniper/graphql/schema.py
netbox_juniper/graphql/types.py
netbox_juniper/migrations/0001_initial.py
netbox_juniper/migrations/0002_securityaddress.py
netbox_juniper/migrations/0003_securityaddressset.py
netbox_juniper/migrations/0004_application_applicationset_and_more.py
netbox_juniper/migrations/0005_applicationset_comments_applicationset_description.py
netbox_juniper/migrations/__init__.py
netbox_juniper/models/__init__.py
netbox_juniper/models/applications.py
netbox_juniper/models/security.py
netbox_juniper/tables/__init__.py
netbox_juniper/tables/applications.py
netbox_juniper/tables/security.py
netbox_juniper/templates/netbox_juniper/application.html
netbox_juniper/templates/netbox_juniper/applicationset.html
netbox_juniper/templates/netbox_juniper/securityaddress.html
netbox_juniper/templates/netbox_juniper/securityaddressset.html
netbox_juniper/templates/netbox_juniper/securityzone.html
netbox_juniper/views/__init__.py
netbox_juniper/views/applications.py
netbox_juniper/views/security.py
netbox_juniper-0.3.dist-info/licenses/LICENSE
netbox_juniper-0.3.dist-info/METADATA
netbox_juniper-0.3.dist-info/WHEEL
netbox_juniper-0.3.dist-info/top_level.txt
netbox_juniper-0.3.dist-info/RECORD
