Metadata-Version: 2.4
Name: netbox-juniper
Version: 0.3
Summary: Juniper Networks Plugin for NetBox.
Home-page: https://github.com/micko/netbox-juniper
Author: Dragan Mickovic
Author-email: Dragan Mickovic <dmickovic@gmail.com>
Project-URL: Homepage, https://github.com/micko/netbox-juniper
Project-URL: Documentation, https://github.com/micko/netbox-juniper/blob/main/docs/using_netbox_juniper.md
Project-URL: Repository, https://github.com/micko/netbox-juniper
Project-URL: Issues, https://github.com/micko/netbox-juniper/issues
Keywords: netbox,netbox-plugin,juniper
Classifier: Development Status :: 3 - Alpha
Classifier: Intended Audience :: Developers
Classifier: Natural Language :: English
Classifier: Programming Language :: Python :: 3 :: Only
Classifier: Programming Language :: Python :: 3.12
Requires-Python: >=3.10
License-File: LICENSE
Dynamic: author
Dynamic: home-page
Dynamic: license-file
